<?xml version="1.0" encoding="UTF-8"?>

<game>
	<users>
		<user>
			<account>admin</account>
			<name>上帝</name>
			<cards>5110043,5110043,5110044,5110044,5110044,5120048,5420049,5420049,5120050,5130051</cards>      <!-- ,8421005,8111006,8421007,8412008,8412009,8522014,8422002 -->
		</user>
		<user>
			<account>chenxian</account>
			<name>陈贤</name>
			<cards>1110053,1110053,1110053,1110054,1110054,1110054,1310055,1120056,1320057,1120059</cards>      <!-- ,8421001,8421010,8421011,8421012,8421013 -->
		</user>
		<user>
			<account>wangzhi</account>
			<name>王智</name>
			<cards></cards>
		</user>
		<user>
			<account>npc</account>
			<name>NPC</name>
			<cards>1130001,1120002,1110004,1140005,1120006,1140007,1230008,1220009,1230010,1210011,1330012,1320013,1420016,1430017,1410018,1440019,1440020</cards>
		</user>
	</users>
</game>